MANIFEST.in
README.rst
setup.py
keras_ding/__init__.py
keras_ding/__version__.py
keras_ding/keras_ding.py
keras_ding.egg-info/PKG-INFO
keras_ding.egg-info/SOURCES.txt
keras_ding.egg-info/dependency_links.txt
keras_ding.egg-info/requires.txt
keras_ding.egg-info/top_level.txt
keras_ding/samples/bojack.wav
keras_ding/samples/ding.wav
keras_ding/samples/pink_guy.wav
keras_ding/samples/rick.wav
keras_ding/samples/whale.wav
keras_ding/utils/__init__.py
keras_ding/utils/invisible_audio.py