Metadata-Version: 2.1
Name: keras-ding
Version: 1.0.5
Summary: Keras callback for playing a sound when training is complete.
Home-page: https://github.com/LucaCappelletti94/keras_ding
Author: Luca Cappelletti
Author-email: cappelletti.luca94@gmail.com
License: MIT
Platform: UNKNOWN
Classifier: Development Status :: 3 - Alpha
Classifier: License :: OSI Approved :: MIT License
Classifier: Programming Language :: Python :: 3
Provides-Extra: test
